MANIFEST.in
pyproject.toml
readme.md
setup.py
pyCombiner/__init__.py
pyCombiner/__main__.py
pyCombiner/inline_imports.py
pyCombiner/locate_module.py
pyCombiner/main.py
pyCombiner/parse_import_line.py
pyCombiner/utils.py
pyCombiner.egg-info/PKG-INFO
pyCombiner.egg-info/SOURCES.txt
pyCombiner.egg-info/dependency_links.txt
pyCombiner.egg-info/entry_points.txt
pyCombiner.egg-info/top_level.txt
pyCombiner/echos/__init__.py
pyCombiner/echos/colorfulPrint.py
pyCombiner/echos/echo.py
pyCombiner/echos/print_tree.py
tests/test_inline_imports.py
tests/test_locate_module.py
tests/test_main.py
tests/test_parse_import_line.py
tests/examples/__init__.py
tests/examples/deep_demo/__init__.py
tests/examples/deep_demo/main.py
tests/examples/deep_demo/module1.py
tests/examples/deep_demo/subdir/__init__.py
tests/examples/deep_demo/subdir/module2.py
tests/examples/deep_demo/subdir/deeper/__init__.py
tests/examples/deep_demo/subdir/deeper/module3.py
tests/examples/deep_demo/subdir/deeper/deepest/__init__.py
tests/examples/deep_demo/subdir/deeper/deepest/module4.py
tests/examples/demo_complicate/__init__.py
tests/examples/demo_complicate/bin.py
tests/examples/demo_complicate/config.py
tests/examples/demo_complicate/runMeCom.py
tests/examples/demo_complicate/service.py
tests/examples/demo_complicate/utils.py
tests/examples/demo_simple/__init__.py
tests/examples/demo_simple/bin.py
tests/examples/demo_simple/runMeSim.py
tests/examples/demo_simple/update.py
tests/examples/demo_simple/utils.py
tests/examples/project2/__init__.py
tests/examples/project2/batches/__init__.py
tests/examples/project2/batches/inspect_all_table.py
tests/examples/project2/tests/__init__.py
tests/examples/project2/tests/settings.py
tests/examples/project2/tests/util/DriverManager.py
tests/examples/project2/tests/util/__init__.py
tests/examples/project2/tests/util/operation.py
tests/examples/project2/tests/util/resource.py
tests/examples/realProject1/__init__.py
tests/examples/realProject1/realTest.py
tests/examples/realProject1/core/__init__.py
tests/examples/realProject1/core/config.py
tests/examples/realProject1/core/debugPrint.py
tests/examples/realProject1/core/getScoreData.py
